{
  "all": [
    4,
    6,
    66.66666666666666,
    [
      "https://github.com/LibrePDF/OpenPDF",
      "https://github.com/plantuml/plantuml",
      "https://github.com/alibaba/Sentinel",
      "https://github.com/mybatis/mybatis-3"
    ]
  ],
  "Complexity": {
    "all": [
      4,
      4,
      100,
      [
        "https://github.com/LibrePDF/OpenPDF",
        "https://github.com/plantuml/plantuml",
        "https://github.com/alibaba/Sentinel",
        "https://github.com/mybatis/mybatis-3"
      ]
    ]
  },
  "ManualChanges": {
    "all": [
      2,
      4,
      50,
      [
        "https://github.com/alibaba/Sentinel",
        "https://github.com/mybatis/mybatis-3"
      ]
    ]
  },
  "RefactoringNotWorthIt": {
    "all": [
      1,
      4,
      25,
      [
        "https://github.com/mybatis/mybatis-3"
      ]
    ]
  },
  "NotEnough": {
    "all": [
      1,
      4,
      25,
      [
        "https://github.com/LibrePDF/OpenPDF"
      ]
    ]
  },
  "SmallerDataClump": {
    "all": [
      2,
      4,
      50,
      [
        "https://github.com/LibrePDF/OpenPDF",
        "https://github.com/plantuml/plantuml"
      ]
    ]
  },
  "LargerDataClump": {
    "all": [
      1,
      4,
      25,
      [
        "https://github.com/LibrePDF/OpenPDF"
      ]
    ]
  },
  "ClassName": {
    "all": [
      1,
      4,
      25,
      [
        "https://github.com/plantuml/plantuml"
      ]
    ]
  },
  "ImportsIssues": {
    "all": [
      1,
      4,
      25,
      [
        "https://github.com/plantuml/plantuml"
      ]
    ]
  },
  "SemanticChanges": {
    "all": [
      1,
      4,
      25,
      [
        "https://github.com/plantuml/plantuml"
      ]
    ]
  }
}