{
  "ValidPrograms": 0.2,
  "RemainingAttemptCount": 1,
  "RemovedDataClumps": 0.02,
  "GitChanges": 26.07,
  "CommentOut": 0.91,
  "ValidJSON": 0.98,
  "NonEmptyResponse": 0.15,
  "ResponseSizeDecrease": 1.08,
  "RichClass": 0,
  "ReferenceErrorOnly": 0.63,
  "RemovedVariables": 2.6,
  "InstructionChangeType=None": 0.05,
  "InstructionChangeType=ReplaceText": 0.04,
  "InstructionChangeType=SpecificLine": 0.85,
  "InstructionChangeType=SpecificLineAll": 0.06,
  "InstructionChangeType=NoneButReplace": 0,
  "DataClumpSize": 4.9,
  "DataClumpOccurence": 15.98,
  "ParametersToParameters": 0.56,
  "FieldToField": 0.2,
  "PreferNonPublic": 0.24,
  "PrimitiveTypes": 0.53,
  "AffectedFiles": 4.29,
  "Time": 38.65,
  "Price": 0.38
}