{
  "mean": 174.16,
  "count": 90,
  "sum": 15674,
  "max": 1121,
  "min": 0,
  "raw": [
    155,
    157,
    214,
    163,
    173,
    172,
    171,
    159,
    190,
    197,
    155,
    195,
    233,
    215,
    186,
    184,
    229,
    280,
    160,
    225,
    158,
    180,
    174,
    250,
    259,
    143,
    256,
    145,
    305,
    262,
    216,
    27,
    0,
    139,
    202,
    178,
    166,
    276,
    142,
    11,
    280,
    92,
    37,
    218,
    30,
    40,
    258,
    56,
    120,
    0,
    258,
    46,
    0,
    239,
    151,
    0,
    36,
    294,
    261,
    224,
    282,
    286,
    279,
    350,
    222,
    0,
    242,
    0,
    0,
    0,
    0,
    292,
    1121,
    273,
    126,
    275,
    155,
    0,
    0,
    287,
    292,
    0,
    88,
    125,
    557,
    0,
    0,
    279,
    2,
    199
  ]
}