{
  "ValidPrograms": [
    0,
    0,
    null,
    1,
    null,
    null,
    null,
    null,
    null,
    null,
    null,
    null,
    1,
    null,
    null,
    null,
    null,
    0,
    0,
    null,
    0,
    0,
    null,
    0,
    null,
    null,
    null,
    0,
    null,
    null
  ],
  "RemainingAttemptCount": [
    0,
    0,
    null,
    1,
    null,
    null,
    null,
    null,
    null,
    null,
    null,
    null,
    5,
    null,
    null,
    null,
    null,
    0,
    0,
    null,
    0,
    0,
    null,
    0,
    null,
    null,
    null,
    0,
    null,
    null
  ],
  "RemovedDataClumps": [
    2.4189512534811968,
    0,
    0,
    0,
    0,
    0,
    0,
    0,
    0,
    0,
    0,
    0,
    0,
    0,
    0,
    0,
    0,
    0.04146024021859773,
    3.76791149496448,
    0,
    0,
    0,
    0,
    0,
    0,
    0,
    0,
    0.3737859289352201,
    0,
    0
  ],
  "GitChanges": [
    232,
    543,
    0,
    149,
    0,
    0,
    0,
    0,
    0,
    0,
    0,
    0,
    0,
    0,
    0,
    0,
    0,
    387,
    64,
    0,
    182,
    143,
    0,
    90,
    0,
    0,
    0,
    181,
    0,
    0
  ],
  "CommentOut": [
    1,
    1,
    null,
    1,
    null,
    null,
    null,
    null,
    null,
    null,
    null,
    null,
    null,
    null,
    null,
    null,
    null,
    1,
    1,
    null,
    0.8333333333333334,
    0.5416666666666667,
    null,
    0.5714285714285714,
    null,
    null,
    null,
    0.9,
    null,
    null
  ],
  "ValidJSON": [
    1,
    1,
    1,
    1,
    1,
    1,
    1,
    1,
    1,
    1,
    1,
    1,
    1,
    1,
    1,
    1,
    1,
    1,
    0.8333333333333334,
    1,
    1,
    1,
    1,
    0.8333333333333334,
    1,
    1,
    1,
    1,
    1,
    1
  ],
  "NonEmptyResponse": [
    1,
    1,
    0,
    1,
    0,
    0,
    0,
    0,
    0,
    0,
    0,
    0,
    1,
    0,
    0,
    0,
    0,
    1,
    0.8333333333333334,
    0,
    1,
    1,
    0,
    0.8333333333333334,
    0,
    0,
    0,
    1,
    0,
    0
  ],
  "ResponseSizeDecrease": [
    0.9659164365046718,
    1.8470588235294119,
    null,
    1.0351453123491359,
    null,
    null,
    null,
    null,
    null,
    null,
    null,
    null,
    null,
    null,
    null,
    null,
    null,
    2.0761710794297352,
    0.8693928321542408,
    null,
    0.9615494568324757,
    1.5090137857900319,
    null,
    1.5035754610462928,
    null,
    null,
    null,
    2.0468284376330352,
    null,
    null
  ],
  "RichClass": [
    0,
    1,
    null,
    0,
    null,
    null,
    null,
    null,
    null,
    null,
    null,
    null,
    null,
    null,
    null,
    null,
    null,
    1,
    0,
    null,
    0,
    null,
    null,
    1,
    1,
    null,
    null,
    1,
    null,
    null
  ],
  "ReferenceErrorOnly": [
    0.5,
    1,
    null,
    0.6,
    null,
    null,
    null,
    null,
    null,
    null,
    null,
    null,
    null,
    null,
    null,
    null,
    null,
    0.8333333333333334,
    0.8333333333333334,
    null,
    1,
    1,
    null,
    1,
    null,
    null,
    null,
    0.5,
    null,
    null
  ],
  "RemovedVariables": [
    39,
    0,
    0,
    0,
    0,
    0,
    0,
    0,
    0,
    0,
    0,
    0,
    0,
    0,
    0,
    0,
    0,
    0,
    110,
    0,
    0,
    5,
    0,
    0,
    0,
    0,
    0,
    7,
    0,
    0
  ],
  "InstructionChangeType=None": [
    0.5,
    0.7586206896551724,
    null,
    0.6666666666666666,
    null,
    null,
    null,
    null,
    null,
    null,
    null,
    null,
    null,
    null,
    null,
    null,
    null,
    0.43333333333333335,
    0.3076923076923077,
    null,
    0.625,
    0,
    null,
    0.35714285714285715,
    null,
    null,
    null,
    0.45,
    null,
    null
  ],
  "InstructionChangeType=ReplaceText": [
    0.10714285714285714,
    0.10344827586206896,
    null,
    0,
    null,
    null,
    null,
    null,
    null,
    null,
    null,
    null,
    null,
    null,
    null,
    null,
    null,
    0.13333333333333333,
    0.07692307692307693,
    null,
    0,
    0.20833333333333334,
    null,
    0,
    null,
    null,
    null,
    0,
    null,
    null
  ],
  "InstructionChangeType=SpecificLine": [
    0.39285714285714285,
    0.13793103448275862,
    null,
    0.25,
    null,
    null,
    null,
    null,
    null,
    null,
    null,
    null,
    null,
    null,
    null,
    null,
    null,
    0.43333333333333335,
    0.6153846153846154,
    null,
    0.375,
    0.75,
    null,
    0.6428571428571429,
    null,
    null,
    null,
    0.45,
    null,
    null
  ],
  "InstructionChangeType=SpecificLineAll": [
    0,
    0,
    null,
    0.08333333333333333,
    null,
    null,
    null,
    null,
    null,
    null,
    null,
    null,
    null,
    null,
    null,
    null,
    null,
    0,
    0,
    null,
    0,
    0.041666666666666664,
    null,
    0,
    null,
    null,
    null,
    0.1,
    null,
    null
  ],
  "InstructionChangeType=NoneButReplace": [
    0,
    0,
    null,
    0,
    null,
    null,
    null,
    null,
    null,
    null,
    null,
    null,
    null,
    null,
    null,
    null,
    null,
    0,
    0,
    null,
    0,
    0,
    null,
    0,
    null,
    null,
    null,
    0,
    null,
    null
  ],
  "DataClumpSize": [
    3,
    3,
    10,
    3,
    5,
    3,
    7,
    3,
    3,
    3,
    5,
    3,
    3,
    10,
    7,
    3,
    5,
    3,
    3,
    10,
    7,
    3,
    5,
    3,
    3,
    10,
    7,
    13,
    3,
    3,
    3,
    3,
    4,
    10,
    3,
    5,
    7,
    3,
    3,
    10,
    3,
    13,
    5,
    3,
    7,
    3,
    3,
    10,
    3,
    3,
    3,
    5,
    3,
    3,
    3,
    16,
    3,
    3,
    6,
    3,
    3,
    3,
    3,
    3,
    3,
    3,
    3,
    5,
    3,
    10,
    7,
    13,
    3,
    3,
    3,
    3,
    3,
    3,
    3,
    3
  ],
  "DataClumpOccurence": [
    2,
    1,
    2,
    5,
    2,
    62,
    6,
    92,
    15,
    2,
    2,
    62,
    1,
    2,
    6,
    2,
    2,
    62,
    1,
    2,
    6,
    2,
    2,
    62,
    1,
    2,
    6,
    2,
    2,
    92,
    1,
    5,
    2,
    2,
    62,
    2,
    6,
    2,
    1,
    2,
    5,
    2,
    2,
    62,
    6,
    15,
    2,
    2,
    2,
    92,
    2,
    2,
    2,
    2,
    3,
    2,
    1,
    2,
    2,
    92,
    2,
    70,
    2,
    15,
    2,
    1,
    2,
    2,
    62,
    2,
    6,
    2,
    1,
    5,
    15,
    2,
    70,
    70,
    92,
    2
  ],
  "ParametersToParameters": [
    1,
    0,
    1,
    1,
    1,
    1,
    1,
    1,
    0,
    1,
    1,
    1,
    0,
    1,
    1,
    1,
    1,
    1,
    0,
    1,
    1,
    1,
    1,
    1,
    0,
    1,
    1,
    0,
    1,
    1,
    0,
    1,
    1,
    1,
    1,
    1,
    1,
    1,
    0,
    1,
    1,
    0,
    1,
    1,
    1,
    0,
    0,
    1,
    0,
    1,
    1,
    1,
    0,
    0,
    0,
    0,
    0,
    0,
    0,
    1,
    0,
    0,
    0,
    0,
    1,
    0,
    1,
    1,
    1,
    1,
    1,
    0,
    0,
    1,
    0,
    0,
    0,
    0,
    1,
    0
  ],
  "FieldToField": [
    0,
    0,
    0,
    0,
    0,
    0,
    0,
    0,
    0,
    0,
    0,
    0,
    0,
    0,
    0,
    0,
    0,
    0,
    0,
    0,
    0,
    0,
    0,
    0,
    0,
    0,
    0,
    1,
    0,
    0,
    0,
    0,
    0,
    0,
    0,
    0,
    0,
    0,
    0,
    0,
    0,
    1,
    0,
    0,
    0,
    0,
    0,
    0,
    0,
    0,
    0,
    0,
    1,
    1,
    0,
    1,
    0,
    1,
    1,
    0,
    1,
    1,
    0,
    0,
    0,
    0,
    0,
    0,
    0,
    0,
    0,
    1,
    0,
    0,
    0,
    0,
    1,
    1,
    0,
    0
  ],
  "PreferNonPublic": [
    0,
    0,
    0,
    0,
    0,
    0,
    0,
    0,
    0,
    0,
    0,
    0,
    0,
    0,
    0,
    0,
    0,
    0,
    0,
    0,
    0,
    0,
    0,
    0,
    0,
    0,
    0,
    1,
    0,
    0,
    0,
    0,
    0,
    0,
    0,
    0,
    0,
    0,
    0,
    0,
    0,
    1,
    0,
    0,
    0,
    0,
    0,
    0,
    1,
    0,
    0,
    0,
    1,
    1,
    0,
    1,
    0,
    1,
    1,
    0,
    1,
    1,
    1,
    0,
    0,
    0,
    0,
    0,
    0,
    0,
    0,
    1,
    0,
    0,
    0,
    1,
    1,
    1,
    0,
    0
  ],
  "PrimitiveTypes": [
    0.6666666666666666,
    0.6666666666666666,
    0.6,
    0.6666666666666666,
    0.8,
    0.6666666666666666,
    0.2857142857142857,
    0.3333333333333333,
    0.6666666666666666,
    0.6666666666666666,
    0.8,
    0.6666666666666666,
    0.6666666666666666,
    0.6,
    0.2857142857142857,
    0.6666666666666666,
    0.8,
    0.6666666666666666,
    0.6666666666666666,
    0.6,
    0.2857142857142857,
    0.6666666666666666,
    0.8,
    0.6666666666666666,
    0.6666666666666666,
    0.6,
    0.2857142857142857,
    0.5384615384615384,
    0.6666666666666666,
    0.3333333333333333,
    0.6666666666666666,
    0.6666666666666666,
    0.25,
    0.6,
    0.6666666666666666,
    0.8,
    0.2857142857142857,
    0.6666666666666666,
    0.6666666666666666,
    0.6,
    0.6666666666666666,
    0.5384615384615384,
    0.8,
    0.6666666666666666,
    0.2857142857142857,
    0.6666666666666666,
    0.3333333333333333,
    0.6,
    0.6666666666666666,
    0.3333333333333333,
    0.6666666666666666,
    0.8,
    0.6666666666666666,
    1,
    1,
    0.5625,
    0.6666666666666666,
    0.6666666666666666,
    0.5,
    0.3333333333333333,
    1,
    0,
    0.6666666666666666,
    0.6666666666666666,
    0.6666666666666666,
    0.6666666666666666,
    0.6666666666666666,
    0.8,
    0.6666666666666666,
    0.6,
    0.2857142857142857,
    0.5384615384615384,
    0.6666666666666666,
    0.6666666666666666,
    0.6666666666666666,
    0.6666666666666666,
    0,
    0,
    0.3333333333333333,
    0.3333333333333333
  ],
  "AffectedFiles": [
    1,
    2,
    1,
    4,
    1,
    4,
    2,
    3,
    10,
    1,
    1,
    4,
    2,
    1,
    2,
    1,
    1,
    4,
    2,
    1,
    2,
    1,
    1,
    4,
    2,
    1,
    2,
    2,
    1,
    3,
    2,
    4,
    1,
    1,
    4,
    1,
    2,
    1,
    2,
    1,
    4,
    2,
    1,
    4,
    2,
    10,
    3,
    1,
    2,
    3,
    1,
    1,
    2,
    2,
    2,
    2,
    2,
    2,
    2,
    3,
    2,
    36,
    2,
    10,
    1,
    2,
    1,
    1,
    4,
    1,
    2,
    2,
    2,
    4,
    10,
    2,
    36,
    36,
    3,
    3
  ],
  "Time": [
    263.46,
    340.56100000000004,
    2.913,
    164.18,
    2.178,
    2.713,
    3.029,
    1.726,
    3.241,
    1.295,
    3.367,
    2.081,
    9.195,
    1.983,
    3.225,
    1.407,
    3.005,
    264.759,
    246.6475,
    3.009,
    164.40000000000003,
    159.186,
    2.978,
    165.218,
    33.053,
    3.226,
    3.551,
    194.39399999999998,
    3.287,
    3.207
  ],
  "Price": [
    1.6992,
    1.7376,
    0.09518,
    1.03119,
    0.09518,
    0.09518,
    0.09518,
    0.09518,
    0.09518,
    0.09518,
    0.09518,
    0.09518,
    0.10346000000000001,
    0.09518,
    0.09518,
    0.09518,
    0.09518,
    1.51823,
    1.56793,
    0.09518,
    1.19146,
    2.3568100000000003,
    0.09518,
    1.46259,
    0.13448000000000002,
    0.09518,
    0.09518,
    1.5706699999999998,
    0.09518,
    0.09518
  ]
}