{
  "ValidPrograms": 1,
  "RemainingAttemptCount": 5,
  "RemovedDataClumps": 7.23,
  "GitChanges": 1711,
  "CommentOut": 1,
  "ValidJSON": 1,
  "NonEmptyResponse": 1,
  "ResponseSizeDecrease": 8.91,
  "RichClass": 1,
  "ReferenceErrorOnly": 1,
  "RemovedVariables": 584,
  "InstructionChangeType=None": 0.82,
  "InstructionChangeType=ReplaceText": 0.43,
  "InstructionChangeType=SpecificLine": 1,
  "InstructionChangeType=SpecificLineAll": 0.2,
  "InstructionChangeType=NoneButReplace": 0.04,
  "DataClumpSize": 25,
  "DataClumpOccurence": 608,
  "ParametersToParameters": 1,
  "FieldToField": 1,
  "PreferNonPublic": 1,
  "PrimitiveTypes": 1,
  "AffectedFiles": 41,
  "Time": 645.26,
  "Price": 3.5
}