{
  "ValidPrograms": 0,
  "RemainingAttemptCount": 0,
  "RemovedDataClumps": 0,
  "GitChanges": 143,
  "CommentOut": 0.5,
  "ValidJSON": 1,
  "NonEmptyResponse": 1,
  "ResponseSizeDecrease": 0.97,
  "RichClass": 0,
  "ReferenceErrorOnly": 0,
  "RemovedVariables": 3,
  "InstructionChangeType=None": 0,
  "InstructionChangeType=ReplaceText": 0,
  "InstructionChangeType=SpecificLine": 0.63,
  "InstructionChangeType=SpecificLineAll": 0,
  "InstructionChangeType=NoneButReplace": 0,
  "DataClumpSize": 3,
  "DataClumpOccurence": 4,
  "ParametersToParameters": 0,
  "FieldToField": 0,
  "PreferNonPublic": 1,
  "PrimitiveTypes": 0,
  "AffectedFiles": 3,
  "Time": 92.75,
  "Price": 0.7
}