{
  "ValidPrograms": 0.16,
  "RemainingAttemptCount": 0.47,
  "RemovedDataClumps": 1.31,
  "GitChanges": 178.61,
  "CommentOut": 0.79,
  "ValidJSON": 0.94,
  "NonEmptyResponse": 0.81,
  "ResponseSizeDecrease": 5.02,
  "RichClass": 0.07,
  "ReferenceErrorOnly": 0.6,
  "RemovedVariables": 60.7,
  "InstructionChangeType=None": 0.37,
  "InstructionChangeType=ReplaceText": 0.05,
  "InstructionChangeType=SpecificLine": 0.48,
  "InstructionChangeType=SpecificLineAll": 0.06,
  "InstructionChangeType=NoneButReplace": 0.03,
  "DataClumpSize": 5.8,
  "DataClumpOccurence": 125.8,
  "ParametersToParameters": 0.65,
  "FieldToField": 0.26,
  "PreferNonPublic": 0.35,
  "PrimitiveTypes": 0.79,
  "AffectedFiles": 12.72,
  "Time": 212.45,
  "Price": 1.14
}