{
  "Surety": 0.28,
  "OutputFormatCorrectness": 0.76,
  "ValidJSON": 0.71,
  "DataClumpSize_mean": 6.86,
  "DataClumpOccurence_mean": 17.83,
  "FieldToField_mean": 0.1,
  "ParametersToParameters_mean": 0.86,
  "DataClumpSize_count": 4.15,
  "DataClumpOccurence_count": 4.15,
  "FieldToField_count": 4.29,
  "ParametersToParameters_count": 4.29,
  "DataClumpSize_sum": 30.94,
  "DataClumpOccurence_sum": 59.75,
  "FieldToField_sum": 0.29,
  "ParametersToParameters_sum": 3.88,
  "DataClumpSize_max": 9.6,
  "DataClumpOccurence_max": 36.25,
  "FieldToField_max": 0.29,
  "ParametersToParameters_max": 0.98,
  "DataClumpSize_min": 208338.21,
  "DataClumpOccurence_min": 208336.52,
  "FieldToField_min": 208333.33,
  "ParametersToParameters_min": 208333.9,
  "DataClumpSize_raw": 0,
  "DataClumpOccurence_raw": 0,
  "FieldToField_raw": 0,
  "ParametersToParameters_raw": 0
}