{
  "Surety": [
    null,
    null,
    1,
    1,
    2,
    null,
    null,
    null,
    null,
    4.5,
    null,
    null,
    null,
    null,
    null,
    null,
    null,
    3,
    null,
    null,
    3,
    null,
    2,
    4,
    3
  ],
  "Number data clumps": [
    0,
    0,
    1,
    1,
    2,
    0,
    0,
    0,
    0,
    5,
    0,
    0,
    0,
    0,
    0,
    0,
    0,
    3,
    0,
    0,
    3,
    0,
    2,
    4,
    3
  ],
  "OutputFormatCorrectness": [
    null,
    null,
    0.5853658536585366,
    0.5925925925925926,
    0.8376068376068376,
    null,
    null,
    null,
    null,
    0.8169014084507042,
    null,
    null,
    null,
    null,
    null,
    null,
    null,
    0.8148148148148148,
    null,
    null,
    0.8148148148148148,
    null,
    0.8376068376068376,
    0.8292682926829268,
    0.8333333333333334
  ],
  "ValidJSON": [
    0,
    0,
    1,
    1,
    1,
    0,
    0,
    0,
    0,
    1,
    0,
    0,
    0,
    0,
    0,
    0,
    0,
    1,
    0,
    0,
    1,
    0,
    1,
    1,
    1
  ],
  "DataClumpSize": [
    5,
    3,
    5,
    11,
    3,
    5,
    3,
    3,
    3,
    3,
    4,
    3,
    3,
    3,
    3,
    3,
    12,
    3,
    3,
    3,
    12,
    3,
    4,
    12
  ],
  "DataClumpOccurence": [
    6,
    6,
    6,
    6,
    6,
    6,
    12,
    2,
    36,
    30,
    6,
    30,
    30,
    30,
    30,
    30,
    2,
    30,
    30,
    30,
    2,
    30,
    6,
    2
  ],
  "ParametersToParameters": [
    1,
    1,
    1,
    1,
    1,
    1,
    1,
    1,
    1,
    1,
    1,
    1,
    1,
    1,
    1,
    1,
    1,
    1,
    1,
    1,
    1,
    1,
    1,
    1
  ],
  "FieldToField": [
    0,
    0,
    0,
    0,
    0,
    0,
    0,
    0,
    0,
    0,
    0,
    0,
    0,
    0,
    0,
    0,
    0,
    0,
    0,
    0,
    0,
    0,
    0,
    0
  ],
  "PreferNonPublic": [
    0,
    0,
    0,
    0,
    0,
    0,
    0,
    0,
    0,
    0,
    0,
    0,
    0,
    0,
    0,
    0,
    0,
    0,
    0,
    0,
    0,
    0,
    0,
    0
  ],
  "PrimitiveTypes": [
    0.2,
    0.3333333333333333,
    0.2,
    0.18181818181818182,
    0.3333333333333333,
    0.2,
    0.3333333333333333,
    0,
    0.6666666666666666,
    1,
    1,
    1,
    1,
    1,
    1,
    1,
    0.75,
    1,
    1,
    1,
    0.75,
    1,
    1,
    0.75
  ],
  "AffectedFiles": [
    3,
    3,
    3,
    3,
    3,
    3,
    4,
    1,
    4,
    1,
    1,
    1,
    1,
    1,
    1,
    1,
    1,
    1,
    1,
    1,
    1,
    1,
    1,
    1
  ]
}