{
  "Surety": 0.39,
  "OutputFormatCorrectness": 0.77,
  "ValidJSON": 0.95,
  "DataClumpSize_mean": 5.31,
  "DataClumpOccurence_mean": 15.36,
  "FieldToField_mean": 0.1,
  "ParametersToParameters_mean": 0.88,
  "DataClumpSize_count": 3,
  "DataClumpOccurence_count": 3,
  "FieldToField_count": 3.05,
  "ParametersToParameters_count": 3.05,
  "DataClumpSize_sum": 17.65,
  "DataClumpOccurence_sum": 50.2,
  "FieldToField_sum": 0.4,
  "ParametersToParameters_sum": 2.6,
  "DataClumpSize_max": 7.4,
  "DataClumpOccurence_max": 27,
  "FieldToField_max": 0.25,
  "ParametersToParameters_max": 1,
  "DataClumpSize_min": 500003.7,
  "DataClumpOccurence_min": 500005.8,
  "FieldToField_min": 0,
  "ParametersToParameters_min": 0.7,
  "DataClumpSize_raw": 0,
  "DataClumpOccurence_raw": 0,
  "FieldToField_raw": 0,
  "ParametersToParameters_raw": 0
}