{
  "Surety": 1.44,
  "OutputFormatCorrectness": 0.77,
  "InvalidJSON": 0.67,
  "DataClumpSize_mean": 6.27,
  "DataClumpOccurence_mean": 13.28,
  "FieldToField_mean": 0.13,
  "ParametersToParameters_mean": 0.85,
  "DataClumpSize_count": 4.12,
  "DataClumpOccurence_count": 4.12,
  "FieldToField_count": 4.25,
  "ParametersToParameters_count": 4.25,
  "DataClumpSize_groupedCount": {
    "11": 2.272727272727273
  },
  "DataClumpOccurence_groupedCount": {
    "2": 2.423076923076923
  },
  "FieldToField_groupedCount": {
    "0": 3.7666666666666666,
    "1": 1.2608695652173914
  },
  "ParametersToParameters_groupedCount": {
    "0": 1.2592592592592593,
    "1": 3.683333333333333
  },
  "DataClumpSize_raw": {
    "0": 5.728813559322034,
    "1": 8,
    "2": 6.428571428571429,
    "3": 5.666666666666667,
    "4": 4.6,
    "5": 5.857142857142857,
    "6": 9.4,
    "7": 11,
    "8": 11,
    "9": 11,
    "10": 9,
    "11": 11
  },
  "DataClumpOccurence_raw": {
    "0": 6.88135593220339,
    "1": 11.584905660377359,
    "2": 16,
    "3": 13.4,
    "4": 28.64,
    "5": 25,
    "6": 9.6,
    "7": 3,
    "8": 3,
    "9": 3.3333333333333335,
    "10": 3.3333333333333335,
    "11": 3.3333333333333335
  },
  "FieldToField_raw": {
    "0": 0,
    "1": 0.2641509433962264,
    "2": 0.14285714285714285,
    "3": 0.16129032258064516,
    "4": 0.04,
    "5": 0.058823529411764705,
    "6": 0.16666666666666666,
    "7": 0,
    "8": 0,
    "9": 0,
    "10": 0,
    "11": 0,
    "12": 0.3333333333333333
  },
  "ParametersToParameters_raw": {
    "0": 0.9833333333333333,
    "1": 0.7358490566037735,
    "2": 0.8571428571428571,
    "3": 0.8387096774193549,
    "4": 0.96,
    "5": 0.8235294117647058,
    "6": 0.6666666666666666,
    "7": 1,
    "8": 1,
    "9": 0.75,
    "10": 1,
    "11": 1,
    "12": 0.6666666666666666
  }
}