{
  "Surety": 2.74,
  "OutputFormatCorrectness": 0.81,
  "ValidJSON": 0.82,
  "DataClumpSize_mean": 7.13,
  "DataClumpOccurence_mean": 4.83,
  "FieldToField_mean": 0.33,
  "ParametersToParameters_mean": 0.66,
  "DataClumpSize_count": 3.16,
  "DataClumpOccurence_count": 3.16,
  "FieldToField_count": 3.22,
  "ParametersToParameters_count": 3.22,
  "DataClumpSize_sum": 22.31,
  "DataClumpOccurence_sum": 17.02,
  "FieldToField_sum": 0.98,
  "ParametersToParameters_sum": 2.2,
  "DataClumpSize_max": 10.56,
  "DataClumpOccurence_max": 10.67,
  "FieldToField_max": 0.84,
  "ParametersToParameters_max": 1,
  "DataClumpSize_min": 3.84,
  "DataClumpOccurence_min": 0.62,
  "FieldToField_min": 0,
  "ParametersToParameters_min": 0.13,
  "DataClumpSize_raw": 0,
  "DataClumpOccurence_raw": 0,
  "FieldToField_raw": 0,
  "ParametersToParameters_raw": 0
}