{
  "mean": 17.93,
  "count": 102,
  "sum": 1829,
  "max": 41,
  "min": 0,
  "raw": [
    3,
    41,
    3,
    41,
    3,
    41,
    3,
    41,
    3,
    3,
    41,
    41,
    41,
    3,
    3,
    41,
    41,
    41,
    3,
    41,
    3,
    41,
    41,
    3,
    3,
    41,
    41,
    41,
    3,
    3,
    41,
    41,
    41,
    3,
    3,
    41,
    41,
    41,
    3,
    3,
    41,
    41,
    41,
    3,
    3,
    41,
    41,
    41,
    3,
    3,
    41,
    41,
    41,
    3,
    41,
    3,
    41,
    3,
    41,
    3,
    41,
    3,
    3,
    41,
    41,
    41,
    3,
    41,
    3,
    41,
    1,
    1,
    2,
    4,
    1,
    2,
    36,
    36,
    3,
    1,
    2,
    2,
    3,
    2,
    2,
    1,
    0,
    0,
    0,
    0,
    0,
    0,
    0,
    0,
    0,
    0,
    0,
    0,
    0,
    0,
    0,
    0
  ]
}