{
  "mean": 7.16,
  "count": 90,
  "sum": 644,
  "max": 75,
  "min": 0,
  "raw": [
    0,
    0,
    0,
    2,
    0,
    0,
    0,
    0,
    0,
    0,
    0,
    0,
    0,
    0,
    0,
    20,
    0,
    0,
    20,
    18,
    0,
    0,
    0,
    0,
    75,
    0,
    60,
    0,
    0,
    0,
    0,
    2,
    0,
    0,
    2,
    0,
    0,
    0,
    0,
    0,
    0,
    0,
    0,
    0,
    0,
    20,
    0,
    50,
    0,
    0,
    0,
    0,
    72,
    0,
    0,
    0,
    0,
    60,
    71,
    0,
    0,
    2,
    0,
    0,
    0,
    0,
    0,
    0,
    0,
    0,
    0,
    0,
    0,
    0,
    0,
    22,
    0,
    0,
    0,
    0,
    0,
    0,
    75,
    73,
    0,
    0,
    0,
    0,
    0,
    0
  ]
}