{
  "ValidPrograms": 15,
  "RemainingAttemptCount": 68,
  "RemovedDataClumps": 475.92,
  "GitChanges": 35758,
  "CommentOut": 79.99,
  "ValidJSON": 173.17,
  "NonEmptyResponse": 148,
  "ResponseSizeDecrease": 1213.9,
  "RichClass": 10,
  "ReferenceErrorOnly": 66.17,
  "RemovedVariables": 27963,
  "InstructionChangeType=None": 57.7,
  "InstructionChangeType=ReplaceText": 10.12,
  "InstructionChangeType=SpecificLine": 68.63,
  "InstructionChangeType=SpecificLineAll": 3.18,
  "InstructionChangeType=NoneButReplace": 13.38,
  "DataClumpSize": 7212,
  "DataClumpOccurence": 249074,
  "ParametersToParameters": 813,
  "FieldToField": 152,
  "PreferNonPublic": 50,
  "PrimitiveTypes": 1034.14,
  "AffectedFiles": 13563,
  "Time": 44500.06,
  "Price": 260.43
}