{
  "ValidPrograms": 0,
  "RemainingAttemptCount": 0,
  "RemovedDataClumps": 79.51,
  "GitChanges": 4697,
  "CommentOut": 14.33,
  "ValidJSON": 28.17,
  "NonEmptyResponse": 20.5,
  "ResponseSizeDecrease": 193.62,
  "RichClass": 0,
  "ReferenceErrorOnly": 9.67,
  "RemovedVariables": 4524,
  "InstructionChangeType=None": 3.45,
  "InstructionChangeType=ReplaceText": 1.97,
  "InstructionChangeType=SpecificLine": 13.39,
  "InstructionChangeType=SpecificLineAll": 0.47,
  "InstructionChangeType=NoneButReplace": 2.72,
  "DataClumpSize": 1157,
  "DataClumpOccurence": 56714,
  "ParametersToParameters": 153,
  "FieldToField": 22,
  "PreferNonPublic": 14,
  "PrimitiveTypes": 189.71,
  "AffectedFiles": 3055,
  "Time": 9090.27,
  "Price": 42.21
}