{
  "mean": 0,
  "count": 15,
  "sum": "5,115,11,11,11,35,11,11,11,35,115,115,11,35,11,11,11,35,11,3,33,113,11,35,11,335,11,3,35,11,35,11,3",
  "max": [
    5,
    11,
    3,
    3
  ],
  "min": 3,
  "raw": [
    [
      5,
      11
    ],
    [
      5,
      11,
      11,
      11,
      3
    ],
    [
      5,
      11,
      11,
      11,
      3
    ],
    [
      5,
      11
    ],
    [
      5,
      11
    ],
    [
      5,
      11,
      3
    ],
    [
      5,
      11,
      11,
      11,
      3
    ],
    [
      5,
      11,
      3,
      3
    ],
    [
      3,
      11
    ],
    [
      3,
      11,
      3
    ],
    [
      5,
      11,
      3
    ],
    [
      3
    ],
    [
      5,
      11,
      3,
      3
    ],
    [
      5,
      11,
      3
    ],
    [
      5,
      11,
      3
    ]
  ]
}