{
  "mean": {
    "0": 1,
    "1": 0.8461538461538461,
    "2": 0.75,
    "3": 0.9,
    "4": 0.875,
    "5": 0.6
  },
  "count": 20,
  "groupedCount": {
    "1": 7,
    "1,1,1,1,1,1": 1,
    "1,1,1,1,1,1,1,1,1,1,1,1,1": 1,
    "1,1,1,1,1,1,1,1,1,1,1,1,1,0": 1,
    "1,1,1,1,1,0": 2,
    "1,1,0,0,1": 1,
    "1,0,1": 1,
    "1,0,0,1": 1,
    "1,1,1,1,0": 1,
    "1,1,1,1": 1,
    "1,1,1,1,1": 1,
    "1,1": 1,
    "1,1,0": 1
  },
  "raw": [
    [
      1,
      1,
      1,
      1,
      1,
      1
    ],
    [
      1,
      1,
      1,
      1,
      1,
      1,
      1,
      1,
      1,
      1,
      1,
      1,
      1
    ],
    [
      1
    ],
    [
      1,
      1,
      1,
      1,
      1,
      1,
      1,
      1,
      1,
      1,
      1,
      1,
      1,
      0
    ],
    [
      1
    ],
    [
      1,
      1,
      1,
      1,
      1,
      0
    ],
    [
      1,
      1,
      0,
      0,
      1
    ],
    [
      1,
      0,
      1
    ],
    [
      1,
      0,
      0,
      1
    ],
    [
      1,
      1,
      1,
      1,
      1,
      0
    ],
    [
      1,
      1,
      1,
      1,
      0
    ],
    [
      1,
      1,
      1,
      1
    ],
    [
      1,
      1,
      1,
      1,
      1
    ],
    [
      1,
      1
    ],
    [
      1
    ],
    [
      1,
      1,
      0
    ],
    [
      1
    ],
    [
      1
    ],
    [
      1
    ],
    [
      1
    ]
  ]
}